vizplugins/__init__.py
vizplugins/cpu_usage.py
vizplugins/memory_usage.py
vizplugins/monitor_process.py
vizplugins/psutil_monitor.py
vizplugins-0.1.3.dist-info/LICENSE
vizplugins-0.1.3.dist-info/METADATA
vizplugins-0.1.3.dist-info/NOTICE.txt
vizplugins-0.1.3.dist-info/WHEEL
vizplugins-0.1.3.dist-info/top_level.txt
vizplugins-0.1.3.dist-info/RECORD
