Metadata-Version: 2.1
Name: vizplugins
Version: 0.1.3
Summary: official plugins for viztracer
Home-page: https://github.com/gaogaotiantian/vizplugins
Author: Tian Gao
Author-email: gaogaotiantian@hotmail.com
License: UNKNOWN
Platform: UNKNOWN
Classifier: Development Status :: 3 - Alpha
Classifier: Programming Language :: Python :: 3.7
Classifier: Programming Language :: Python :: 3.8
Classifier: Programming Language :: Python :: 3.9
Classifier: Programming Language :: Python :: 3.10
Classifier: Programming Language :: Python :: 3.11
Classifier: Intended Audience :: Developers
Classifier: License :: OSI Approved :: Apache Software License
Classifier: Operating System :: OS Independent
Requires-Python: >=3.7
License-File: LICENSE
License-File: NOTICE.txt
Requires-Dist: psutil
